{
	"id": "5739fff1-03fe-4f20-aa1b-35ccfeba8c9b",
	"name": "eCommerceAPITests",
	"values": [
		{
			"key": "product_url",
			"value": "http://localhost/prog8185w4/api/product",
			"type": "default",
			"enabled": true
		},
		{
			"key": "product_id",
			"value": "1",
			"type": "default",
			"enabled": true
		},
		{
			"key": "product_name_update",
			"value": "PRODUCT NAME UPDATE",
			"type": "default",
			"enabled": true
		},
		{
			"key": "user_url",
			"value": "http://localhost/prog8185w4/api/user",
			"type": "default",
			"enabled": true
		},
		{
			"key": "user_id",
			"value": "1",
			"type": "default",
			"enabled": true
		},
		{
			"key": "user_name_update",
			"value": "USER NAME UPDATE",
			"type": "default",
			"enabled": true
		},
		{
			"key": "cart_url",
			"value": "http://localhost/prog8185w4/api/cart",
			"type": "default",
			"enabled": true
		},
		{
			"key": "cart_product_init_qty",
			"value": "3",
			"type": "default",
			"enabled": true
		},
		{
			"key": "cart_product_update_qty",
			"value": "2",
			"type": "default",
			"enabled": true
		},
		{
			"key": "cart_product_changed_qty",
			"value": "1",
			"type": "default",
			"enabled": true
		},
		{
			"key": "product_id_2",
			"value": "",
			"type": "any",
			"enabled": true
		},
		{
			"key": "order_url",
			"value": "http://localhost/prog8185w4/api/order",
			"type": "default",
			"enabled": true
		},
		{
			"key": "comments_url",
			"value": "http://localhost/prog8185w4/api/comments",
			"type": "default",
			"enabled": true
		},
		{
			"key": "comment_id",
			"value": "1",
			"type": "default",
			"enabled": true
		},
		{
			"key": "comment_rating_update",
			"value": "2",
			"type": "default",
			"enabled": true
		},
		{
			"key": "comment_image_update",
			"value": "test_tst.png",
			"type": "default",
			"enabled": true
		},
		{
			"key": "comment_text_update",
			"value": "Not so great product.",
			"type": "default",
			"enabled": true
		},
		{
			"key": "user_id_2",
			"value": "1",
			"type": "default",
			"enabled": true
		},
		{
			"key": "order_id",
			"value": "1",
			"type": "default",
			"enabled": true
		}
	],
	"_postman_variable_scope": "environment",
	"_postman_exported_at": "2022-07-05T20:39:19.437Z",
	"_postman_exported_using": "Postman/9.23.3"
}